autochatbot/__init__.py
autochatbot/chat.py
autochatbot/clean.py
AutoChatbot-0.1.1.dist-info/LICENSE
AutoChatbot-0.1.1.dist-info/METADATA
AutoChatbot-0.1.1.dist-info/WHEEL
AutoChatbot-0.1.1.dist-info/top_level.txt
AutoChatbot-0.1.1.dist-info/RECORD
