Metadata-Version: 2.1
Name: AutoChatbot
Version: 0.1.1
Summary: Package that makes chatbots automatically
Home-page: https://github.com/kritikseth
Author: Kritik Seth
Author-email: sethkritik@gmail.com
License: UNKNOWN
Project-URL: Documentation, https://kritikseth.github.io/autochatbot_docs
Platform: UNKNOWN
Classifier: Programming Language :: Python :: 3
Classifier: License :: OSI Approved :: MIT License
Classifier: Operating System :: OS Independent
Requires-Python: >=3.6
Requires-Dist: tensorflow
Requires-Dist: keras
Requires-Dist: gensim
Requires-Dist: re
Requires-Dist: numpy
Requires-Dist: tqdm
Requires-Dist: pandas
Requires-Dist: contractions
Requires-Dist: pycontractions
Requires-Dist: unicodedata
